alist_kits/__init__.py
alist_kits/alistapi.py
alist_kits/attribute.py
alist_kits/objects.py
alist_kits-0.2.dist-info/LICENSE
alist_kits-0.2.dist-info/METADATA
alist_kits-0.2.dist-info/WHEEL
alist_kits-0.2.dist-info/top_level.txt
alist_kits-0.2.dist-info/zip-safe
alist_kits-0.2.dist-info/RECORD
